jenkins_mcp_enterprise-1.0.0.dist-info/licenses/LICENSE
mcp_server/__init__.py
mcp_server/base.py
mcp_server/cache_manager.py
mcp_server/cleanup_manager.py
mcp_server/cli.py
mcp_server/config.py
mcp_server/config_factory.py
mcp_server/di_container.py
mcp_server/exceptions.py
mcp_server/http_server.py
mcp_server/logging_config.py
mcp_server/multi_jenkins_manager.py
mcp_server/retry_utils.py
mcp_server/server.py
mcp_server/tool_factory.py
mcp_server/tool_validator.py
mcp_server/utils.py
mcp_server/vector_manager.py
mcp_server/diagnostic_config/diagnostic-parameters.yml
jenkins_mcp_enterprise-1.0.0.dist-info/METADATA
jenkins_mcp_enterprise-1.0.0.dist-info/WHEEL
jenkins_mcp_enterprise-1.0.0.dist-info/entry_points.txt
jenkins_mcp_enterprise-1.0.0.dist-info/top_level.txt
jenkins_mcp_enterprise-1.0.0.dist-info/RECORD
