Metadata-Version: 2.4
Name: jenkins-mcp-enterprise
Version: 1.0.0
Summary: MCP server for Jenkins integration with AI assistants, providing build management, log analysis, and failure diagnostics.
Author-email: Jordan Jarvis <your.email@domain.com>
Maintainer-email: Jordan Jarvis <your.email@domain.com>
License:                     GNU GENERAL PUBLIC LICENSE
Project-URL: Homepage, https://github.com/Jordan-Jarvis/jenkins-mcp-enterprise
Project-URL: Repository, https://github.com/Jordan-Jarvis/jenkins-mcp-enterprise
Project-URL: Documentation, https://github.com/Jordan-Jarvis/jenkins-mcp-enterprise/blob/main/README.md
Project-URL: Issues, https://github.com/Jordan-Jarvis/jenkins-mcp-enterprise/issues
Keywords: jenkins,mcp,ai,devops,model-context-protocol
Classifier: Development Status :: 5 - Production/Stable
Classifier: Intended Audience :: Developers
Classifier: Topic :: Software Development :: Build Tools
Classifier: License :: OSI Approved :: GNU General Public License v3 (GPLv3)
Classifier: Programming Language :: Python :: 3
Classifier: Programming Language :: Python :: 3.10
Classifier: Programming Language :: Python :: 3.11
Classifier: Programming Language :: Python :: 3.12
Requires-Python: >=3.10
License-File: LICENSE
Requires-Dist: python-jenkins>=1.8.2
Requires-Dist: requests>=2.31.0
Requires-Dist: sentence-transformers>=2.2.0
Requires-Dist: qdrant-client>=1.14.3
Requires-Dist: tiktoken>=0.5.0
Requires-Dist: APScheduler>=3.11.0
Requires-Dist: modelcontextprotocol>=0.1.0
Requires-Dist: fastapi>=0.100.0
Requires-Dist: uvicorn>=0.23.0
Requires-Dist: httpx>=0.24.0
Requires-Dist: websockets>=11.0
Requires-Dist: sse-starlette>=1.6.0
Requires-Dist: pyyaml>=6.0
Provides-Extra: dev
Requires-Dist: pytest>=7.4.0; extra == "dev"
Requires-Dist: pytest-asyncio>=0.21.0; extra == "dev"
Requires-Dist: pytest-cov>=4.1.0; extra == "dev"
Dynamic: license-file
